colourpy/__init__.py
colourpy/colourpy.py
colourpy-0.1.0.dist-info/LICENCE
colourpy-0.1.0.dist-info/METADATA
colourpy-0.1.0.dist-info/WHEEL
colourpy-0.1.0.dist-info/top_level.txt
colourpy-0.1.0.dist-info/RECORD
