Metadata-Version: 2.1
Name: colourpy
Version: 0.1.0
Summary: A package inspired by simple chalk which colours terminal text with 256 Colour support
Home-page: https://github.com/blue-horizons/pyColour
Author: Joshua Cotugno
Author-email: jdcotugno006@gmail.com
License: UNKNOWN
Project-URL: Bug Tracker, https://github.com/blue-horizons/pyColour/issues
Platform: UNKNOWN
Classifier: Programming Language :: Python :: 3
Classifier: License :: OSI Approved :: MIT License
Classifier: Operating System :: OS Independent
Requires-Python: >=3.6
License-File: LICENCE
